{"url": "https://www.neptun.mk/categories/ONE-BOX_SISTEMI/MIKADOMD-601KP", "title": "ONE-BOX СИСТЕМ MIKADOMD-601KP", "warranty": "24", "regular_price": "12.999", "happy_price": "9.999", "description": ["Портабл звучник\nБоја:црна\nОсветлување\nВлезни приклучоци:Bluetooth/USB/AUX/Microphone/Memory Card/FM Radio\nИзлезни приклучоци:6.35mm AUX 8 ohm, 30W or 3.5mm Headphone Jack\nBluetooth: V.5.0\nFm радио\nFm радио френквенција:88-108 MHZ\nUSB:USB Type A Female\nМикрофон:безжичен\nФренквенција на микрофон:100Hz - 16 KHz\nБатерија на микрофон:2 алкални 1.5V\nПодесување на звук\nМоќност на звучник:Speaker: 30Watt, 2.Speaker:10 Watt\nДијаметар на звучник:прв звучник-17цм, 2 звучник-2цм\nБатерија:7.4V, 3000mAh, литиум јонска\nВреметраење на полнење батерија:2-4 батерии\nДолжина на кабел:100цм\nТежина:5.80Kg\nГолемина:300x265x565mm"]}