{
    "url": "https://www.neptun.mk/categories/LICNA_NEGA_I_UBAVINA_RAZNO/3M-AURA-9320-",
    "title": "ЗАШТИТНА МАСКА 3M AURA 9320+",
    "warranty": "",
    "regular_price": "199",
    "happy_price": "145",
    "description": {
        "Материјалот за филтер со напреден 3M™": "true",
        "Им помага на носителите да дишат лесно преку респираторот за поудобна заштита": "true",
        "Уникатен дизајн со 3 панели": "true",
        "Овозможува поголеми движења на лицето за време на говорот": "true",
        "Го намалува замаглувањето на очилата": "true",
        "Заштита FFP2 - заштита од прашина и магла во широк спектар": "true"
    },
    "category": "Phone case",
    "image": "https://www.neptun.mk/2021/10/30/Aura9320PackshotF20210211095039_8212e885-9991-49c9-b12a-198043742078.jpg"
}