{
    "url": "https://www.neptun.mk/categories/Gaming_tastaturi/CANYON-Deimos-GK-4-Rainbow-CND-SKB4-US-Wired-Black",
    "title": "CANYON DEIMOS GK-4 RAINBOW CND-SKB4-US WIRED BLACK",
    "warranty": "24",
    "regular_price": "2.499",
    "happy_price": "",
    "description": {
        "Механичка тастатура": "true",
        "104 механички копчиња": "true",
        "Сини механички прекинувачи": "true",
        "Активирање на тастерот 4,0mm": "true",
        "50 милиони притискање на копче": "true",
        "Anti-ghosting функции": "true",
        "Заклучување на копчето „Windows/Start“": "true",
        "20 видови на позадинско осветлување": "true"
    }
}