{
    "url": "https://www.neptun.mk/categories/GLUVCINA/EVEREST-SMW-444-Usb-Silver-2-4Ghz-Optical-Wireless-Mouse",
    "title": "EVEREST SMW-444 USB SILVER 2.4GHZ OPTICAL WIRELESS MOUSE",
    "warranty": "24",
    "regular_price": "299",
    "happy_price": "",
    "description": {
        "Wireless Mouse": "True",
        "Резолуција": "800/1200 DPI",
        "Конекција": "USB 2.0",
        "Работно растојание": "10m"
    },
    "category": "Mouse",
    "image": "https://www.neptun.mk/2024/04/05/3896200_3f9e9ca9-fe1d-4332-857b-5d9be6836e0a.jpg"
}