{
    "url": "https://www.neptun.mk/categories/televizori/PHILIPS-65-PUS-7608-",
    "title": "4K UHD LED SMART TV PHILIPS 65 PUS 7608 , 65\"(165.1CM), DUAL CORE",
    "warranty": "24",
    "regular_price": "44.999",
    "happy_price": "32.999",
    "description": {
        "65\"(165.1cm) 4k UHD LED SMART TV": "true",
        "Резолуција": "3840 x 2160",
        "Dual Core процесор": "true",
        "Dolby Vision and Dolby Atmos": "true",
        "Звучник": "20W",
        "HDR10+/HLG": "true",
        "Pixel Precise Ultra HD": "true",
        "Dolby Vision": "true",
        "YouTube, Netflix TV, Amazon Prime Video": "true",
        "Конекција": "true",
        "3 x HDMI": "true",
        "2 x USB": "true",
        "CI+": "true",
        "LAN": "true",
        "Wi-Fi 802.11n, 2 x 2, Dual band": "true",
        "Bluetooth 5.0": "true",
        "DVB-T/T2/T2-HD/C/S/S2": "true"
    },
    "category": "Television",
    "image": "https://www.neptun.mk/2023/09/05/0102_33d03cb5-1b93-4434-a4a4-02e3196456f2.JPG"
}