{
    "url": "https://www.neptun.mk/categories/televizori/PHILIPS-43-PUS-7608",
    "title": "4K UHD SMART LED PHILIPS 43 PUS 7608 43\"(108CM) HDR10+",
    "warranty": "24",
    "regular_price": "22.999",
    "happy_price": "18.999",
    "description": {
        "43\"(108cm) 4k UHD SMART LED": "True",
        "Резолуција": "3840 x 2160",
        "Pixel Precise Ultra HD": "True",
        "HDR10+": "True",
        "HLG (Hybrid Log Gamma)": "True",
        "Dolby Vision": "True",
        "Звучник": "20W RMS",
        "Dolby Atmos®": "True",
        "Конекција": "True",
        "3 x HDMI": "True",
        "2x USB": "True",
        "LAN": "True",
        "1 x Component (Y/Pb/Pr)": "True",
        "1 x Digital Audio излез (Optical)": "True",
        "1 x CI+ Card Slot": "True",
        "DVB-T/T2/T2-HD/C/S/S2": "True",
        "WiFi вградено": "True"
    },
    "category": "Television"
}