{
    "url": "https://www.neptun.mk/categories/Gaming_slusalki/PS5-Pulse-3D-Wireless-Headset-Black",
    "title": "GAMING СЛУШАЛКИ ЗА PS5 PULSE 3D WIRELESS HEADSET BLACK",
    "warranty": "12",
    "regular_price": "6.199",
    "happy_price": "",
    "description": {
        "Бежични слушалки": "True",
        "Компатибилни со": "PS4, PS5, Windows, macOS®",
        "Built-in Microphone x2": "True",
        "Microphone noise-canceling": "True",
        "Полнење": "2часа",
        "Батерија": "12часа",
        "3.5mm приклучок": "True",
        "USB Type-C приклучок": "True"
    }
}