{
    "url": "https://www.neptun.mk/categories/Gaming_mouse/REDRAGON-Storm-Elite-M988-RGB",
    "title": "MOUSE REDRAGON STORM ELITE M988-RGB",
    "warranty": "12",
    "regular_price": "1.899",
    "happy_price": "",
    "description": {
        "Глушец": "True",
        "8 копчиња": "True",
        "USB конекција": "True",
        "20 милјони кликање": "True",
        "DPI 16000": "True"
    },
    "category": "Mouse",
    "image": "https://www.neptun.mk/2021/02/17/1_80f4a420-95d7-4043-b47c-cdb82b47a070.JPG"
}