{
    "url": "https://www.neptun.mk/categories/monitori1/SAMSUNG-LS-28G700-NUXEN",
    "title": "МОНИТОР SAMSUNG LS 28G700NUXEN, 28\"(71CM), 144HZ, 1MS",
    "warranty": "24",
    "regular_price": "41.999",
    "happy_price": "32.995",
    "description": {
        "Монитор": "True",
        "Екран": "28\"(71см)",
        "Резолуција": "(3.840 x 2.160)",
        "Сооднос на слика": "16:9",
        "Вид на панел": "IPS",
        "Светлина": "300 cd/㎡",
        "Брзина на освежување": "Max 144Hz",
        "Статичен сооднос на контраст": "1000:1",
        "Време на одговор": "1ms(G/G)",
        "Агол на гледање (хоризонтален/вертикален)": "178°/178°",
        "Поддршка за боја": "Max 16.7M",
        "Режим Eye Saver": "True",
        "Flicker Free": "True",
        "FreeSync Premium Pro": "True",
        "Слика во слика": "True",
        "HDMI": "True",
        "USB": "True"
    },
    "category": "Monitor"
}