{
    "url": "https://www.neptun.mk/categories/BOJLERI/TR5001-21-24-27-ESOB",
    "title": "TR5001 21/24/27 ESOB",
    "warranty": "24",
    "regular_price": "24.999",
    "happy_price": "",
    "description": {
        "TR5001 21/24/27 ESOB електронски проточен бојлер": "true",
        "Енергетска класа": "А",
        "Работен притисок": "0.25 бари",
        "Регулатор на моќноста": "21/24/27kW",
        "Заштеда на ел.енергија,со едноставно прилагодување на прекинувачот на контролната електроника": "true",
        "Подготвен за Wi-Fi поврзување преку дополнителен адаптер (кој се докупува )": "true",
        "Годишна потрошувачка на енергија": "476 kWh",
        "Бучавост": "15 dB",
        "Kaпацитет на топла вода во минута": "14,6л/13,2л/7,2 л/мин. (380С/600С)",
        "Заштеда на енергија до 30% во споредба со хидраулични прот.бојлери": "true",
        "CLICKFIX plus": "true",
        "Сигурност": "Заштита IP25,осигурач 32 А,-трофазно"
    },
    "category": "Appliances",
    "image": "https://www.neptun.mk/2024/05/20/TR5001-2.jpg"
}